seno/__init__.py
seno_jonatan-0.0.1.dist-info/LICENSE
seno_jonatan-0.0.1.dist-info/METADATA
seno_jonatan-0.0.1.dist-info/WHEEL
seno_jonatan-0.0.1.dist-info/top_level.txt
seno_jonatan-0.0.1.dist-info/RECORD
