Metadata-Version: 2.1
Name: seno-jonatan
Version: 0.0.1
Summary: se no
Home-page: https://github.com/pypa/sampleproject
Author: Jonatan
Author-email: contact@pornhub.com
License: UNKNOWN
Project-URL: Bug Tracker, https://github.com/pypa/sampleproject/issues
Platform: UNKNOWN
Classifier: Programming Language :: Python :: 3
Classifier: License :: OSI Approved :: MIT License
Classifier: Operating System :: OS Independent
Requires-Python: >=3.8
License-File: LICENSE
